antclient/__init__.py
antclient/client.py
antclient/sql.py
antclient-0.3.0.dist-info/licenses/LICENSE
antclient-0.3.0.dist-info/METADATA
antclient-0.3.0.dist-info/WHEEL
antclient-0.3.0.dist-info/top_level.txt
antclient-0.3.0.dist-info/RECORD
