Metadata-Version: 2.4
Name: antclient
Version: 0.3.0
Summary: Python client for Anthive REST API - query single-cell expression databases
Home-page: https://github.com/yourusername/anthive
Author: Anthive Team
Author-email: Anthive Team <anthive@example.com>
Maintainer-email: Anthive Team <anthive@example.com>
License: MIT
Project-URL: Homepage, https://github.com/yourusername/anthive
Project-URL: Documentation, https://github.com/yourusername/anthive
Project-URL: Repository, https://github.com/yourusername/anthive
Project-URL: Bug Tracker, https://github.com/yourusername/anthive/issues
Project-URL: Changelog, https://github.com/yourusername/anthive/blob/main/antclient/CHANGELOG.md
Keywords: single-cell,genomics,bioinformatics,expression,scRNA-seq,database,API,client
Classifier: Development Status :: 4 - Beta
Classifier: Intended Audience :: Science/Research
Classifier: Intended Audience :: Developers
Classifier: Topic :: Scientific/Engineering :: Bio-Informatics
Classifier: Topic :: Database
Classifier: License :: OSI Approved :: MIT License
Classifier: Programming Language :: Python :: 3
Classifier: Programming Language :: Python :: 3.8
Classifier: Programming Language :: Python :: 3.9
Classifier: Programming Language :: Python :: 3.10
Classifier: Programming Language :: Python :: 3.11
Classifier: Programming Language :: Python :: 3.12
Classifier: Operating System :: OS Independent
Classifier: Typing :: Typed
Requires-Python: >=3.8
License-File: LICENSE
Requires-Dist: requests>=2.25.0
Requires-Dist: pandas>=1.3.0
Provides-Extra: widgets
Requires-Dist: ipywidgets>=7.6.0; extra == "widgets"
Provides-Extra: dev
Requires-Dist: pytest>=7.0.0; extra == "dev"
Requires-Dist: pytest-cov>=4.0.0; extra == "dev"
Requires-Dist: black>=22.0.0; extra == "dev"
Requires-Dist: flake8>=4.0.0; extra == "dev"
Requires-Dist: build>=0.10.0; extra == "dev"
Requires-Dist: twine>=4.0.0; extra == "dev"
Dynamic: author
Dynamic: home-page
Dynamic: license-file
Dynamic: requires-python
